detect_gh_actions_unused_secrets.py
detect_gh_actions_unused_secrets-0.6.0.dist-info/licenses/LICENSE
detect_gh_actions_unused_secrets-0.6.0.dist-info/METADATA
detect_gh_actions_unused_secrets-0.6.0.dist-info/WHEEL
detect_gh_actions_unused_secrets-0.6.0.dist-info/entry_points.txt
detect_gh_actions_unused_secrets-0.6.0.dist-info/top_level.txt
detect_gh_actions_unused_secrets-0.6.0.dist-info/RECORD
