Metadata-Version: 2.4
Name: detect_gh_actions_unused_secrets
Version: 0.6.0
Summary: Detects secrets that are defined in the repository and are not used in Github Actions
Home-page: https://github.com/artemrys/detect-gh-actions-unused-secrets
Author: Artem Rys
Author-email: rysartem@gmail.com
License: MIT
Classifier: License :: OSI Approved :: MIT License
Classifier: Programming Language :: Python :: 3
Classifier: Programming Language :: Python :: 3 :: Only
Classifier: Programming Language :: Python :: 3.9
Classifier: Programming Language :: Python :: 3.10
Classifier: Programming Language :: Python :: 3.11
Classifier: Programming Language :: Python :: 3.12
Classifier: Programming Language :: Python :: 3.13
Classifier: Programming Language :: Python :: Implementation :: CPython
Classifier: Programming Language :: Python :: Implementation :: PyPy
Requires-Python: >=3.9
License-File: LICENSE
Dynamic: license-file
